README.md
setup.py
pulumi_netbox/__init__.py
pulumi_netbox/_inputs.py
pulumi_netbox/_utilities.py
pulumi_netbox/aggregate.py
pulumi_netbox/available_ip_address.py
pulumi_netbox/available_prefix.py
pulumi_netbox/circuit.py
pulumi_netbox/circuit_provider.py
pulumi_netbox/circuit_termination.py
pulumi_netbox/circuit_type.py
pulumi_netbox/cluster.py
pulumi_netbox/cluster_group.py
pulumi_netbox/cluster_type.py
pulumi_netbox/custom_field.py
pulumi_netbox/device.py
pulumi_netbox/device_role.py
pulumi_netbox/device_type.py
pulumi_netbox/get_cluster.py
pulumi_netbox/get_cluster_group.py
pulumi_netbox/get_cluster_type.py
pulumi_netbox/get_device_role.py
pulumi_netbox/get_device_type.py
pulumi_netbox/get_interfaces.py
pulumi_netbox/get_ip_addresses.py
pulumi_netbox/get_ip_range.py
pulumi_netbox/get_platform.py
pulumi_netbox/get_prefix.py
pulumi_netbox/get_region.py
pulumi_netbox/get_site.py
pulumi_netbox/get_tag.py
pulumi_netbox/get_tenant.py
pulumi_netbox/get_tenant_group.py
pulumi_netbox/get_tenants.py
pulumi_netbox/get_virtual_machines.py
pulumi_netbox/get_vlan.py
pulumi_netbox/get_vrf.py
pulumi_netbox/interface.py
pulumi_netbox/ip_address.py
pulumi_netbox/ip_range.py
pulumi_netbox/ipam_role.py
pulumi_netbox/manufacturer.py
pulumi_netbox/outputs.py
pulumi_netbox/platform.py
pulumi_netbox/prefix.py
pulumi_netbox/primary_ip.py
pulumi_netbox/provider.py
pulumi_netbox/pulumi-plugin.json
pulumi_netbox/py.typed
pulumi_netbox/region.py
pulumi_netbox/rir.py
pulumi_netbox/service.py
pulumi_netbox/site.py
pulumi_netbox/tag.py
pulumi_netbox/tenant.py
pulumi_netbox/tenant_group.py
pulumi_netbox/token.py
pulumi_netbox/user.py
pulumi_netbox/virtual_machine.py
pulumi_netbox/vlan.py
pulumi_netbox/vrf.py
pulumi_netbox.egg-info/PKG-INFO
pulumi_netbox.egg-info/SOURCES.txt
pulumi_netbox.egg-info/dependency_links.txt
pulumi_netbox.egg-info/not-zip-safe
pulumi_netbox.egg-info/requires.txt
pulumi_netbox.egg-info/top_level.txt
pulumi_netbox/config/__init__.py
pulumi_netbox/config/vars.py