Metadata-Version: 2.1
Name: pulumi-netbox
Version: 0.0.3
Summary: A Pulumi package for creating and managing Netbox resources.
Home-page: https://github.com/hbjydev/pulumi-netbox
License: Apache-2.0
Project-URL: Repository, https://github.com/hbjydev/pulumi-netbox
Keywords: pulumi netbox category/cloud
Platform: UNKNOWN
